listtypes/__init__.py
listtypes/listtypes.py
listtypes-1.0.1.dist-info/METADATA
listtypes-1.0.1.dist-info/WHEEL
listtypes-1.0.1.dist-info/RECORD
